{
    "palette": "blue",
    "header": {
        "title": "PRIVACY",
        "has_nav": true,
        "nav_links": [
            {
                "label": "Home",
                "url": "/"
            },
            {
                "label": "Features",
                "url": "/features"
            },
            {
                "label": "Pricing",
                "url": "/pricing"
            },
            {
                "label": "Style Guide",
                "url": "/style-guide"
            },
            {
                "label": "Sign Up",
                "url": "/signup",
                "primary": true
            }
        ]
    },
    "footer": {
        "tagline": "PRIVACY",
        "has_nav": true,
        "nav_title": "Company",
        "nav_links": [
            {
                "label": "About Us",
                "url": "/about"
            },
            {
                "label": "Blog",
                "url": "/blog"
            },
            {
                "label": "Sign Up",
                "url": "signup"
            },
            {
                "label": "Contact",
                "url": "/contact"
            }
        ],
        "has_social": true,
        "social_title": "Community",
        "social_links": [
            {
                "label": "Twitter",
                "url": "https://twitter.com/",
                "new_window": true
            },
            {
                "label": "Instagram",
                "url": "https://www.instagram.com/",
                "new_window": true
            },
            {
                "label": "LinkedIn",
                "url": "https://www.linkedin.com/",
                "new_window": true
            }
        ],
        "has_subscribe": true,
        "subscribe_title": "Email Us",
        "subscribe_content": "privacy@email.com",
        "content": "&copy; Privacy. All rights reserved.",
        "links": [
            {
                "label": "Privacy",
                "url": "https://festive-saturn-aa528.netlify.app/",
                "new_window": false,
                "primary": true
            },
            {
                "label": "lorem-ipsum",
                "url": "lorem-ipsum",
                "primary": false,
                "new_window": true,
                "type": "action"
            }
        ]
    },
    "title": "Privacy"
}